nemf/__init__.py
nemf/caller.py
nemf/decorators.py
nemf/interaction_functions.py
nemf/models.py
nemf/plot.py
nemf/worker.py
tests/__init__.py
tests/conftest.py
tests/test_forward.py
tests/test_import.py
tests/test_inverse.py
tests/test_visualisation.py
nemf-0.3.4.dist-info/LICENSE
nemf-0.3.4.dist-info/METADATA
nemf-0.3.4.dist-info/WHEEL
nemf-0.3.4.dist-info/top_level.txt
nemf-0.3.4.dist-info/RECORD
