Metadata-Version: 2.1
Name: nemf
Version: 0.3.4
Summary: Network-based ecosystem Modelling Framework
Home-page: https://github.com/465b/nemf/
Author: Laurin Steidle
Author-email: laurin.steidle@uni-hamburg.de
License: BSD
Keywords: ecosystem modelling framework inverse-modelling
Platform: UNKNOWN
Classifier: License :: OSI Approved :: BSD License
Classifier: Programming Language :: Python :: 3
Classifier: Topic :: Scientific/Engineering
Classifier: Intended Audience :: Science/Research
Classifier: Operating System :: POSIX :: Linux
Classifier: Development Status :: 3 - Alpha
Requires-Dist: numpy
Requires-Dist: seaborn
Requires-Dist: pandas
Requires-Dist: matplotlib
Requires-Dist: networkx
Requires-Dist: pyyaml
Requires-Dist: termcolor
